{
  "_class": "MSImmutableHotspotLayer",
  "booleanOperation": 0,
  "do_objectID": "934C2D04-9D09-4707-A68A-EC23E81FC397",
  "exportOptions": {
    "_class": "exportOptions",
    "do_objectID": "4F5E8950-A3DE-4259-B9A5-78A1E9BE4A37",
    "exportFormats": [
    ],
    "includedLayerIds": [
    ],
    "layerOptions": 0,
    "shouldTrim": false
  },
  "flow": {
    "_class": "MSImmutableFlowConnection",
    "animationType": -1,
    "destinationArtboardID": "",
    "do_objectID": "C1B9653D-A86F-4D10-9F37-C6FD235D17B2"
  },
  "frame": {
    "_class": "rect",
    "constrainProportions": false,
    "do_objectID": "0C6D0DFB-175B-405E-B723-366599F68B6B",
    "height": 48,
    "width": 90,
    "x": 95,
    "y": 0
  },
  "isFixedToViewport": false,
  "isFlippedHorizontal": false,
  "isFlippedVertical": false,
  "isLocked": false,
  "isVisible": true,
  "layerListExpandedType": 0,
  "name": "Hotspot - Tab 2",
  "nameIsFixed": true,
  "resizingConstraint": 18,
  "resizingType": 0,
  "rotation": 0,
  "shouldBreakMaskChain": false
}